[{
  "nameAndAge": "\n          Plants vs. Zombies‪™‬\n 9+\n",
  "describe": "\n                      #4 trong Giải Đố\n                    ",
  "rating": "4,7 • 138,1 N đánh giá",
  "company": "\n              EA Swiss Sarl\n          ",
  "size": "150,8 MB",
  "price": "Miễn phí"
},
{
  "nameAndAge": "\n          Hero Adventure\n 17+\n",
  "describe": "\n                      #3 trong Phiêu Lưu\n                    ",
  "rating": "",
  "company": "\n              NGUYEN TOANH\n          ",
  "size": "30 MB",
  "price": "19.000đ"
},
{
  "nameAndAge": "\n          My Talking Angela\n 4+\n",
  "describe": "\n                      #7 trong Gia Đình\n                    ",
  "rating": "4,4 • 110,3 N đánh giá",
  "company": "\n              Outfit7 Limited\n          ",
  "size": "429 MB",
  "price": "Miễn phí"
},
{
  "nameAndAge": "\n          Doggo Go - ghép hình, game vui\n 4+\n",
  "describe": "\n                      #3 trong Board Game\n                    ",
  "rating": "4,1 • 38,8 N đánh giá",
  "company": "\n              Nox Interactive Technology Limited\n          ",
  "size": "199,6 MB",
  "price": "Miễn phí"
},
{
  "nameAndAge": "\n          Bridge Constructor\n 4+\n",
  "describe": "\n                      #3 trong Giải Đố\n                    ",
  "rating": "4,8 • 32 đánh giá",
  "company": "\n              Headup GmbH\n          ",
  "size": "161,7 MB",
  "price": "29.000đ"
}]